beautiful_code_generator/__init__.py
beautiful_code_generator/generator.py
beautiful_code_generator-0.0.1.dist-info/LICENSE
beautiful_code_generator-0.0.1.dist-info/METADATA
beautiful_code_generator-0.0.1.dist-info/WHEEL
beautiful_code_generator-0.0.1.dist-info/top_level.txt
beautiful_code_generator-0.0.1.dist-info/RECORD
