Metadata-Version: 2.1
Name: beautiful_code_generator
Version: 0.0.1
Summary: Simple tools that generates beautiful code
Home-page: UNKNOWN
Author: Johny Utah
Author-email: jones.hovercraft2020@gmail.com
License: UNKNOWN
Keywords: python,beautiful code generator,code generator
Platform: UNKNOWN
Classifier: Development Status :: 3 - Alpha
Classifier: Intended Audience :: Education
Classifier: Programming Language :: Python :: 2
Classifier: Programming Language :: Python :: 3
Classifier: Operating System :: MacOS :: MacOS X
Classifier: Operating System :: Microsoft :: Windows
License-File: LICENSE
